ros_get/__init__.py
ros_get/__main__.py
ros_get/commands.py
ros_get/utils.py
ros_get/workspace.py
ros_get-0.5.0.dist-info/LICENSE
ros_get-0.5.0.dist-info/METADATA
ros_get-0.5.0.dist-info/WHEEL
ros_get-0.5.0.dist-info/entry_points.txt
ros_get-0.5.0.dist-info/top_level.txt
ros_get-0.5.0.dist-info/RECORD
