Metadata-Version: 2.1
Name: ros-get
Version: 0.5.0
Summary: Simple tools for working with ROS source packages
Home-page: https://github.com/Rayman/ros-get
Author: Ramon Wijnands
Author-email: rayman747@hotmail.com
License: MIT
Platform: UNKNOWN
License-File: LICENSE
Requires-Dist: argcomplete
Requires-Dist: catkin-pkg
Requires-Dist: catkin-tools
Requires-Dist: colorlog
Requires-Dist: future
Requires-Dist: rosdep
Requires-Dist: rosdistro (>=0.7.3)
Requires-Dist: rosinstall-generator
Requires-Dist: six (>=1.7)
Requires-Dist: trollius
Requires-Dist: vcstools
Requires-Dist: xdg (==1.0.7)
Requires-Dist: mock (<4) ; python_version < "3"
Requires-Dist: colcon-common-extensions ; python_version >= "3"
